llm_llama_cpp.py
llm_llama_cpp-0.3.dist-info/LICENSE
llm_llama_cpp-0.3.dist-info/METADATA
llm_llama_cpp-0.3.dist-info/WHEEL
llm_llama_cpp-0.3.dist-info/entry_points.txt
llm_llama_cpp-0.3.dist-info/top_level.txt
llm_llama_cpp-0.3.dist-info/RECORD
