Metadata-Version: 2.1
Name: llm-llama-cpp
Version: 0.3
Summary: LLM plugin for running models using llama.cpp
Author: Simon Willison
License: Apache-2.0
Project-URL: Homepage, https://github.com/simonw/llm-llama-cpp
Project-URL: Changelog, https://github.com/simonw/llm-llama-cpp/releases
Project-URL: Issues, https://github.com/simonw/llm-llama-cpp/issues
Project-URL: CI, https://github.com/simonw/llm-llama-cpp/actions
Classifier: License :: OSI Approved :: Apache Software License
License-File: LICENSE
Requires-Dist: llm
Requires-Dist: httpx
Provides-Extra: test
Requires-Dist: pytest ; extra == 'test'
